avi_tools/__init__.py
avi_tools/async_funcs_manager/__init__.py
avi_tools/twillkit/__init__.py
avi_tools/variabledb/__init__.py
avi_tools-1.0.9.dist-info/licenses/LICENSE
avi_tools-1.0.9.dist-info/METADATA
avi_tools-1.0.9.dist-info/WHEEL
avi_tools-1.0.9.dist-info/top_level.txt
avi_tools-1.0.9.dist-info/RECORD
