Metadata-Version: 2.4
Name: avi_tools
Version: 1.0.9
Summary: Avi's Python toolkit including async function manager, variable database, and terminal utilities.
Author-email: Avi Twil <avitwil@gmail.com>
License-Expression: MIT
Project-URL: Homepage, https://pypi.org/project/avi_tools/
Project-URL: Repository, https://github.com/avitwil/avi_tools
Classifier: Programming Language :: Python :: 3
Classifier: Operating System :: OS Independent
Requires-Python: >=3.8
License-File: LICENSE
Requires-Dist: dill>=0.3.8
Dynamic: license-file
